httpx_ws/__init__.py
httpx_ws/_api.py
httpx_ws/_exceptions.py
httpx_ws/_ping.py
httpx_ws/py.typed
httpx_ws/transport.py
httpx_ws-0.6.1.dist-info/METADATA
httpx_ws-0.6.1.dist-info/WHEEL
httpx_ws-0.6.1.dist-info/licenses/LICENSE
httpx_ws-0.6.1.dist-info/RECORD
