Metadata-Version: 2.3
Name: httpx-ws
Version: 0.6.1
Summary: WebSockets support for HTTPX
Project-URL: Documentation, https://frankie567.github.io/httpx-ws/
Project-URL: Source, https://github.com/frankie567/httpx-ws
Author-email: François Voron <fvoron@gmail.com>
License-File: LICENSE
Classifier: Development Status :: 4 - Beta
Classifier: Framework :: AsyncIO
Classifier: Intended Audience :: Developers
Classifier: License :: OSI Approved :: MIT License
Classifier: Programming Language :: Python :: 3 :: Only
Classifier: Programming Language :: Python :: 3.8
Classifier: Programming Language :: Python :: 3.9
Classifier: Programming Language :: Python :: 3.10
Classifier: Programming Language :: Python :: 3.11
Classifier: Programming Language :: Python :: 3.12
Classifier: Topic :: Internet :: WWW/HTTP :: Session
Requires-Python: >=3.8
Requires-Dist: anyio>=4
Requires-Dist: httpcore>=1.0.4
Requires-Dist: httpx>=0.23.1
Requires-Dist: wsproto
